cajCvtPdf/__init__.py
cajCvtPdf/cli.py
cajCvtPdf/bin/caj2pdf.exe
cajCvtPdf/bin/libjbig2codec.dll
cajCvtPdf/bin/libjbigdec.dll
cajCvtPdf/bin/mutool.exe
cajcvtpdf-0.1.2.dist-info/METADATA
cajcvtpdf-0.1.2.dist-info/WHEEL
cajcvtpdf-0.1.2.dist-info/entry_points.txt
cajcvtpdf-0.1.2.dist-info/top_level.txt
cajcvtpdf-0.1.2.dist-info/RECORD
