Metadata-Version: 2.4
Name: cajCvtPdf
Version: 0.1.2
Summary: A caj2pdf tool
Home-page: https://github.com/caj2pdf/caj2pdf
Author: Null Name
Author-email: email@example.com
Dynamic: author
Dynamic: author-email
Dynamic: description
Dynamic: description-content-type
Dynamic: home-page
Dynamic: summary
